{"Valid":true,"Guid":"9bd17347-9425-4559-8177-364d7bd861da","UserId":"84ad7456-6c25-4965-92d5-613d9be274c6","ExpectedTime":2,"ExpectedMoves":2,"MinimumMovesWithFlag":2,"Difficulty":66,"StartNode":{"x":3.0,"y":7.0},"EndNode":{"x":3.0,"y":3.0},"Elements":["","","","","","","","","","","","","","","","","","","","","","","","","(N)","","","","","","","(P)(V)","","","","","","","(N)(F)","(P)(H)(S)(DD)","","","","","","(P)(V)","","","","","","","(N)","","","","","","","","","","","","","","","","","","","","","","","",""]}